jupyterlab_sql/__init__.py
jupyterlab_sql/cache.py
jupyterlab_sql/connection_url.py
jupyterlab_sql/executor.py
jupyterlab_sql/handlers.py
jupyterlab_sql/request_decoder.py
jupyterlab_sql/responses.py
jupyterlab_sql/schema_loader.py
jupyterlab_sql/serializer.py
jupyterlab_sql/version.py
jupyterlab_sql/schemas/database-structure.json
jupyterlab_sql/schemas/sql-query.json
jupyterlab_sql/schemas/table-structure.json
jupyterlab_sql/tests/__init__.py
jupyterlab_sql/tests/test_cache.py
jupyterlab_sql/tests/test_connection_url.py
jupyterlab_sql/tests/test_request_decoder.py
jupyterlab_sql/tests/test_schema_loader.py
jupyterlab_sql/tests/test_serializer.py
jupyterlab_sql-0.2.1.data/data/share/jupyter/lab/extensions/jupyterlab-sql-0.2.1.tgz
jupyterlab_sql-0.2.1.dist-info/LICENSE.txt
jupyterlab_sql-0.2.1.dist-info/METADATA
jupyterlab_sql-0.2.1.dist-info/WHEEL
jupyterlab_sql-0.2.1.dist-info/top_level.txt
jupyterlab_sql-0.2.1.dist-info/RECORD
