Metadata-Version: 2.1
Name: jupyterlab-sql
Version: 0.2.1
Summary: UNKNOWN
Home-page: UNKNOWN
License: UNKNOWN
Platform: UNKNOWN
Requires-Python: >=3.5
Requires-Dist: jupyterlab
Requires-Dist: sqlalchemy
Requires-Dist: jsonschema (>=3)
